{
  "symbol": "BTCUSD_ecn",
  "generated_at": "2026-04-08T02:37:08.313181+00:00",
  "lookback_periods": 30,
  "current_price": 71277.0,
  "candles": {
    "1h": [
      {
        "time": "2026-04-06T21:00:00+00:00",
        "open": 69581.0,
        "high": 69958.0,
        "low": 69470.0,
        "close": 69901.0,
        "tick_volume": 7932,
        "spread": 200,
        "real_volume": 0
      },
      {
        "time": "2026-04-06T22:00:00+00:00",
        "open": 69893.0,
        "high": 69912.0,
        "low": 69581.0,
        "close": 69698.0,
        "tick_volume": 6091,
        "spread": 0,
        "real_volume": 0
      },
      {
        "time": "2026-04-06T23:00:00+00:00",
        "open": 69713.0,
        "high": 69995.0,
        "low": 69599.0,
        "close": 69815.0,
        "tick_volume": 4327,
        "spread": 200,
        "real_volume": 0
      },
      {
        "time": "2026-04-07T00:00:00+00:00",
        "open": 69703.0,
        "high": 69773.0,
        "low": 69420.0,
        "close": 69519.0,
        "tick_volume": 4373,
        "spread": 200,
        "real_volume": 0
      },
      {
        "time": "2026-04-07T01:00:00+00:00",
        "open": 69520.0,
        "high": 69599.0,
        "low": 68782.0,
        "close": 68808.0,
        "tick_volume": 7718,
        "spread": 200,
        "real_volume": 0
      },
      {
        "time": "2026-04-07T02:00:00+00:00",
        "open": 68785.0,
        "high": 68920.0,
        "low": 68302.0,
        "close": 68850.0,
        "tick_volume": 10202,
        "spread": 50,
        "real_volume": 0
      },
      {
        "time": "2026-04-07T03:00:00+00:00",
        "open": 68847.0,
        "high": 69137.0,
        "low": 68713.0,
        "close": 68773.0,
        "tick_volume": 9731,
        "spread": 0,
        "real_volume": 0
      },
      {
        "time": "2026-04-07T04:00:00+00:00",
        "open": 68773.0,
        "high": 68908.0,
        "low": 68325.0,
        "close": 68405.0,
        "tick_volume": 10087,
        "spread": 200,
        "real_volume": 0
      },
      {
        "time": "2026-04-07T05:00:00+00:00",
        "open": 68403.0,
        "high": 68714.0,
        "low": 68257.0,
        "close": 68661.0,
        "tick_volume": 6975,
        "spread": 200,
        "real_volume": 0
      },
      {
        "time": "2026-04-07T06:00:00+00:00",
        "open": 68662.0,
        "high": 68808.0,
        "low": 68608.0,
        "close": 68772.0,
        "tick_volume": 4988,
        "spread": 200,
        "real_volume": 0
      },
      {
        "time": "2026-04-07T07:00:00+00:00",
        "open": 68773.0,
        "high": 68997.0,
        "low": 68529.0,
        "close": 68858.0,
        "tick_volume": 6546,
        "spread": 200,
        "real_volume": 0
      },
      {
        "time": "2026-04-07T08:00:00+00:00",
        "open": 68858.0,
        "high": 68873.0,
        "low": 68584.0,
        "close": 68665.0,
        "tick_volume": 5533,
        "spread": 200,
        "real_volume": 0
      },
      {
        "time": "2026-04-07T09:00:00+00:00",
        "open": 68663.0,
        "high": 68665.0,
        "low": 68421.0,
        "close": 68566.0,
        "tick_volume": 6503,
        "spread": 200,
        "real_volume": 0
      },
      {
        "time": "2026-04-07T10:00:00+00:00",
        "open": 68567.0,
        "high": 68710.0,
        "low": 68490.0,
        "close": 68619.0,
        "tick_volume": 5455,
        "spread": 300,
        "real_volume": 0
      },
      {
        "time": "2026-04-07T11:00:00+00:00",
        "open": 68620.0,
        "high": 69003.0,
        "low": 68597.0,
        "close": 68944.0,
        "tick_volume": 8673,
        "spread": 300,
        "real_volume": 0
      },
      {
        "time": "2026-04-07T12:00:00+00:00",
        "open": 68944.0,
        "high": 69260.0,
        "low": 68921.0,
        "close": 69150.0,
        "tick_volume": 6978,
        "spread": 100,
        "real_volume": 0
      },
      {
        "time": "2026-04-07T13:00:00+00:00",
        "open": 69148.0,
        "high": 69215.0,
        "low": 68168.0,
        "close": 68234.0,
        "tick_volume": 10241,
        "spread": 200,
        "real_volume": 0
      },
      {
        "time": "2026-04-07T14:00:00+00:00",
        "open": 68233.0,
        "high": 68453.0,
        "low": 68051.0,
        "close": 68332.0,
        "tick_volume": 6305,
        "spread": 200,
        "real_volume": 0
      },
      {
        "time": "2026-04-07T15:00:00+00:00",
        "open": 68330.0,
        "high": 68575.96,
        "low": 68056.0,
        "close": 68394.0,
        "tick_volume": 7617,
        "spread": 0,
        "real_volume": 0
      },
      {
        "time": "2026-04-07T16:00:00+00:00",
        "open": 68390.0,
        "high": 68618.66,
        "low": 68176.0,
        "close": 68225.0,
        "tick_volume": 9933,
        "spread": 0,
        "real_volume": 0
      },
      {
        "time": "2026-04-07T17:00:00+00:00",
        "open": 68223.0,
        "high": 68259.0,
        "low": 67748.0,
        "close": 67844.0,
        "tick_volume": 14933,
        "spread": 100,
        "real_volume": 0
      },
      {
        "time": "2026-04-07T18:00:00+00:00",
        "open": 67843.0,
        "high": 68251.0,
        "low": 67708.0,
        "close": 68153.0,
        "tick_volume": 10722,
        "spread": 200,
        "real_volume": 0
      },
      {
        "time": "2026-04-07T19:00:00+00:00",
        "open": 68151.0,
        "high": 68450.0,
        "low": 68059.0,
        "close": 68227.0,
        "tick_volume": 9792,
        "spread": 200,
        "real_volume": 0
      },
      {
        "time": "2026-04-07T20:00:00+00:00",
        "open": 68226.0,
        "high": 68995.0,
        "low": 68157.0,
        "close": 68695.0,
        "tick_volume": 8644,
        "spread": 200,
        "real_volume": 0
      },
      {
        "time": "2026-04-07T21:00:00+00:00",
        "open": 68704.0,
        "high": 68773.0,
        "low": 68300.0,
        "close": 68434.0,
        "tick_volume": 7545,
        "spread": 200,
        "real_volume": 0
      },
      {
        "time": "2026-04-07T22:00:00+00:00",
        "open": 68433.0,
        "high": 69090.0,
        "low": 68318.0,
        "close": 68994.0,
        "tick_volume": 13080,
        "spread": 200,
        "real_volume": 0
      },
      {
        "time": "2026-04-07T23:00:00+00:00",
        "open": 69012.0,
        "high": 69545.0,
        "low": 69012.0,
        "close": 69318.0,
        "tick_volume": 10474,
        "spread": 200,
        "real_volume": 0
      },
      {
        "time": "2026-04-08T00:00:00+00:00",
        "open": 69292.0,
        "high": 70214.0,
        "low": 69292.0,
        "close": 69918.0,
        "tick_volume": 12361,
        "spread": 0,
        "real_volume": 0
      },
      {
        "time": "2026-04-08T01:00:00+00:00",
        "open": 69918.0,
        "high": 71516.0,
        "low": 69909.0,
        "close": 71509.0,
        "tick_volume": 18183,
        "spread": 100,
        "real_volume": 0
      },
      {
        "time": "2026-04-08T02:00:00+00:00",
        "open": 71508.0,
        "high": 72756.0,
        "low": 71162.0,
        "close": 71914.0,
        "tick_volume": 19851,
        "spread": 200,
        "real_volume": 0
      }
    ],
    "4h": [
      {
        "time": "2026-04-01T04:00:00+00:00",
        "open": 68272.0,
        "high": 68421.0,
        "low": 67500.0,
        "close": 68262.0,
        "tick_volume": 26296,
        "spread": 100,
        "real_volume": 0
      },
      {
        "time": "2026-04-01T08:00:00+00:00",
        "open": 68262.0,
        "high": 69271.0,
        "low": 68100.0,
        "close": 68650.0,
        "tick_volume": 35413,
        "spread": 100,
        "real_volume": 0
      },
      {
        "time": "2026-04-01T12:00:00+00:00",
        "open": 68650.0,
        "high": 68768.0,
        "low": 68226.0,
        "close": 68373.0,
        "tick_volume": 30211,
        "spread": 100,
        "real_volume": 0
      },
      {
        "time": "2026-04-01T16:00:00+00:00",
        "open": 68376.0,
        "high": 68982.0,
        "low": 67894.0,
        "close": 68798.0,
        "tick_volume": 49532,
        "spread": 100,
        "real_volume": 0
      },
      {
        "time": "2026-04-01T20:00:00+00:00",
        "open": 68801.0,
        "high": 69162.0,
        "low": 67913.0,
        "close": 68194.0,
        "tick_volume": 36958,
        "spread": 0,
        "real_volume": 0
      },
      {
        "time": "2026-04-02T00:00:00+00:00",
        "open": 68183.0,
        "high": 68662.0,
        "low": 67982.0,
        "close": 68599.0,
        "tick_volume": 28939,
        "spread": 0,
        "real_volume": 0
      },
      {
        "time": "2026-04-02T04:00:00+00:00",
        "open": 68601.0,
        "high": 68601.0,
        "low": 66170.0,
        "close": 66314.0,
        "tick_volume": 53456,
        "spread": 100,
        "real_volume": 0
      },
      {
        "time": "2026-04-02T08:00:00+00:00",
        "open": 66315.0,
        "high": 66926.0,
        "low": 66265.0,
        "close": 66427.0,
        "tick_volume": 27339,
        "spread": 200,
        "real_volume": 0
      },
      {
        "time": "2026-04-02T12:00:00+00:00",
        "open": 66427.0,
        "high": 66506.0,
        "low": 65925.0,
        "close": 66028.0,
        "tick_volume": 30200,
        "spread": 100,
        "real_volume": 0
      },
      {
        "time": "2026-04-02T16:00:00+00:00",
        "open": 66029.0,
        "high": 67279.0,
        "low": 65680.0,
        "close": 67084.0,
        "tick_volume": 62567,
        "spread": 100,
        "real_volume": 0
      },
      {
        "time": "2026-04-02T20:00:00+00:00",
        "open": 67082.0,
        "high": 67436.0,
        "low": 66586.0,
        "close": 66940.0,
        "tick_volume": 31886,
        "spread": 0,
        "real_volume": 0
      },
      {
        "time": "2026-04-03T00:00:00+00:00",
        "open": 66886.0,
        "high": 67100.0,
        "low": 66691.0,
        "close": 66783.0,
        "tick_volume": 23284,
        "spread": 0,
        "real_volume": 0
      },
      {
        "time": "2026-04-03T04:00:00+00:00",
        "open": 66784.0,
        "high": 66905.0,
        "low": 66257.0,
        "close": 66613.0,
        "tick_volume": 30477,
        "spread": 50,
        "real_volume": 0
      },
      {
        "time": "2026-04-03T08:00:00+00:00",
        "open": 66614.0,
        "high": 67293.0,
        "low": 66413.0,
        "close": 66971.0,
        "tick_volume": 29301,
        "spread": 300,
        "real_volume": 0
      },
      {
        "time": "2026-04-03T12:00:00+00:00",
        "open": 66960.0,
        "high": 67387.0,
        "low": 66617.0,
        "close": 66733.0,
        "tick_volume": 26798,
        "spread": 300,
        "real_volume": 0
      },
      {
        "time": "2026-04-03T16:00:00+00:00",
        "open": 66734.0,
        "high": 67070.0,
        "low": 66508.0,
        "close": 66998.0,
        "tick_volume": 25521,
        "spread": 100,
        "real_volume": 0
      },
      {
        "time": "2026-04-03T20:00:00+00:00",
        "open": 67000.0,
        "high": 67075.0,
        "low": 66741.0,
        "close": 66827.0,
        "tick_volume": 14410,
        "spread": 100,
        "real_volume": 0
      },
      {
        "time": "2026-04-06T00:00:00+00:00",
        "open": 67519.0,
        "high": 69570.0,
        "low": 67306.0,
        "close": 69066.0,
        "tick_volume": 41194,
        "spread": 0,
        "real_volume": 0
      },
      {
        "time": "2026-04-06T04:00:00+00:00",
        "open": 69067.0,
        "high": 69399.0,
        "low": 68720.0,
        "close": 69119.0,
        "tick_volume": 33932,
        "spread": 200,
        "real_volume": 0
      },
      {
        "time": "2026-04-06T08:00:00+00:00",
        "open": 69119.0,
        "high": 69351.0,
        "low": 68755.0,
        "close": 69217.0,
        "tick_volume": 28241,
        "spread": 100,
        "real_volume": 0
      },
      {
        "time": "2026-04-06T12:00:00+00:00",
        "open": 69218.0,
        "high": 70269.0,
        "low": 69190.0,
        "close": 69376.0,
        "tick_volume": 30003,
        "spread": 50,
        "real_volume": 0
      },
      {
        "time": "2026-04-06T16:00:00+00:00",
        "open": 69380.0,
        "high": 70370.0,
        "low": 69121.0,
        "close": 69822.0,
        "tick_volume": 48916,
        "spread": 100,
        "real_volume": 0
      },
      {
        "time": "2026-04-06T20:00:00+00:00",
        "open": 69818.0,
        "high": 69995.0,
        "low": 69262.0,
        "close": 69815.0,
        "tick_volume": 29840,
        "spread": 0,
        "real_volume": 0
      },
      {
        "time": "2026-04-07T00:00:00+00:00",
        "open": 69703.0,
        "high": 69773.0,
        "low": 68302.0,
        "close": 68773.0,
        "tick_volume": 32024,
        "spread": 0,
        "real_volume": 0
      },
      {
        "time": "2026-04-07T04:00:00+00:00",
        "open": 68773.0,
        "high": 68997.0,
        "low": 68257.0,
        "close": 68858.0,
        "tick_volume": 28596,
        "spread": 200,
        "real_volume": 0
      },
      {
        "time": "2026-04-07T08:00:00+00:00",
        "open": 68858.0,
        "high": 69003.0,
        "low": 68421.0,
        "close": 68944.0,
        "tick_volume": 26164,
        "spread": 200,
        "real_volume": 0
      },
      {
        "time": "2026-04-07T12:00:00+00:00",
        "open": 68944.0,
        "high": 69260.0,
        "low": 68051.0,
        "close": 68394.0,
        "tick_volume": 31141,
        "spread": 0,
        "real_volume": 0
      },
      {
        "time": "2026-04-07T16:00:00+00:00",
        "open": 68390.0,
        "high": 68618.66,
        "low": 67708.0,
        "close": 68227.0,
        "tick_volume": 45380,
        "spread": 0,
        "real_volume": 0
      },
      {
        "time": "2026-04-07T20:00:00+00:00",
        "open": 68226.0,
        "high": 69545.0,
        "low": 68157.0,
        "close": 69318.0,
        "tick_volume": 39743,
        "spread": 200,
        "real_volume": 0
      },
      {
        "time": "2026-04-08T00:00:00+00:00",
        "open": 69292.0,
        "high": 72756.0,
        "low": 69292.0,
        "close": 71709.0,
        "tick_volume": 62800,
        "spread": 0,
        "real_volume": 0
      }
    ],
    "day": [
      {
        "time": "2026-02-26T00:00:00+00:00",
        "open": 69060.0,
        "high": 69218.0,
        "low": 66480.0,
        "close": 67480.0,
        "tick_volume": 349412,
        "spread": 0,
        "real_volume": 0
      },
      {
        "time": "2026-02-27T00:00:00+00:00",
        "open": 67473.0,
        "high": 68243.0,
        "low": 65089.0,
        "close": 65542.0,
        "tick_volume": 303521,
        "spread": 0,
        "real_volume": 0
      },
      {
        "time": "2026-03-02T00:00:00+00:00",
        "open": 65712.0,
        "high": 70130.0,
        "low": 65010.0,
        "close": 69439.0,
        "tick_volume": 362248,
        "spread": 0,
        "real_volume": 0
      },
      {
        "time": "2026-03-03T00:00:00+00:00",
        "open": 69367.0,
        "high": 69538.0,
        "low": 66121.0,
        "close": 68037.0,
        "tick_volume": 374453,
        "spread": 0,
        "real_volume": 0
      },
      {
        "time": "2026-03-04T00:00:00+00:00",
        "open": 68252.0,
        "high": 74082.0,
        "low": 67358.0,
        "close": 73351.0,
        "tick_volume": 344354,
        "spread": 0,
        "real_volume": 0
      },
      {
        "time": "2026-03-05T00:00:00+00:00",
        "open": 73451.0,
        "high": 73594.0,
        "low": 70637.0,
        "close": 71146.0,
        "tick_volume": 298443,
        "spread": 0,
        "real_volume": 0
      },
      {
        "time": "2026-03-06T00:00:00+00:00",
        "open": 71065.0,
        "high": 71448.0,
        "low": 67739.0,
        "close": 68319.0,
        "tick_volume": 325523,
        "spread": 0,
        "real_volume": 0
      },
      {
        "time": "2026-03-09T00:00:00+00:00",
        "open": 67216.0,
        "high": 69533.0,
        "low": 65579.0,
        "close": 68964.0,
        "tick_volume": 323502,
        "spread": 0,
        "real_volume": 0
      },
      {
        "time": "2026-03-10T00:00:00+00:00",
        "open": 69024.0,
        "high": 71800.0,
        "low": 68366.0,
        "close": 70262.0,
        "tick_volume": 305474,
        "spread": 0,
        "real_volume": 0
      },
      {
        "time": "2026-03-11T00:00:00+00:00",
        "open": 70303.0,
        "high": 71373.0,
        "low": 68970.0,
        "close": 70610.0,
        "tick_volume": 283449,
        "spread": 0,
        "real_volume": 0
      },
      {
        "time": "2026-03-12T00:00:00+00:00",
        "open": 70619.0,
        "high": 70962.0,
        "low": 69189.0,
        "close": 70190.0,
        "tick_volume": 268898,
        "spread": 0,
        "real_volume": 0
      },
      {
        "time": "2026-03-13T00:00:00+00:00",
        "open": 70274.0,
        "high": 73941.0,
        "low": 70027.0,
        "close": 71364.0,
        "tick_volume": 309077,
        "spread": 0,
        "real_volume": 0
      },
      {
        "time": "2026-03-16T00:00:00+00:00",
        "open": 71682.0,
        "high": 74547.0,
        "low": 71538.0,
        "close": 74227.0,
        "tick_volume": 282441,
        "spread": 0,
        "real_volume": 0
      },
      {
        "time": "2026-03-17T00:00:00+00:00",
        "open": 74354.0,
        "high": 76006.0,
        "low": 73398.0,
        "close": 74538.0,
        "tick_volume": 284101,
        "spread": 0,
        "real_volume": 0
      },
      {
        "time": "2026-03-18T00:00:00+00:00",
        "open": 74498.0,
        "high": 74829.0,
        "low": 70467.0,
        "close": 71222.0,
        "tick_volume": 255477,
        "spread": 0,
        "real_volume": 0
      },
      {
        "time": "2026-03-19T00:00:00+00:00",
        "open": 71268.0,
        "high": 71622.0,
        "low": 68731.0,
        "close": 70467.0,
        "tick_volume": 270257,
        "spread": 0,
        "real_volume": 0
      },
      {
        "time": "2026-03-20T00:00:00+00:00",
        "open": 70462.0,
        "high": 71374.0,
        "low": 69352.0,
        "close": 70040.0,
        "tick_volume": 244280,
        "spread": 0,
        "real_volume": 0
      },
      {
        "time": "2026-03-23T00:00:00+00:00",
        "open": 68032.0,
        "high": 71813.0,
        "low": 67278.0,
        "close": 70882.0,
        "tick_volume": 334570,
        "spread": 0,
        "real_volume": 0
      },
      {
        "time": "2026-03-24T00:00:00+00:00",
        "open": 70796.0,
        "high": 71400.0,
        "low": 68842.0,
        "close": 70063.0,
        "tick_volume": 280995,
        "spread": 0,
        "real_volume": 0
      },
      {
        "time": "2026-03-25T00:00:00+00:00",
        "open": 70041.0,
        "high": 72035.0,
        "low": 69810.0,
        "close": 70984.0,
        "tick_volume": 230148,
        "spread": 0,
        "real_volume": 0
      },
      {
        "time": "2026-03-26T00:00:00+00:00",
        "open": 70935.0,
        "high": 71562.0,
        "low": 68066.0,
        "close": 68958.0,
        "tick_volume": 226379,
        "spread": 0,
        "real_volume": 0
      },
      {
        "time": "2026-03-27T00:00:00+00:00",
        "open": 68852.0,
        "high": 69144.0,
        "low": 65482.0,
        "close": 65972.0,
        "tick_volume": 242487,
        "spread": 0,
        "real_volume": 0
      },
      {
        "time": "2026-03-30T00:00:00+00:00",
        "open": 66497.0,
        "high": 68120.0,
        "low": 64920.0,
        "close": 66515.0,
        "tick_volume": 258694,
        "spread": 0,
        "real_volume": 0
      },
      {
        "time": "2026-03-31T00:00:00+00:00",
        "open": 66539.0,
        "high": 68532.0,
        "low": 65916.0,
        "close": 68203.0,
        "tick_volume": 252573,
        "spread": 0,
        "real_volume": 0
      },
      {
        "time": "2026-04-01T00:00:00+00:00",
        "open": 68007.0,
        "high": 69271.0,
        "low": 67500.0,
        "close": 68194.0,
        "tick_volume": 203836,
        "spread": 0,
        "real_volume": 0
      },
      {
        "time": "2026-04-02T00:00:00+00:00",
        "open": 68183.0,
        "high": 68662.0,
        "low": 65680.0,
        "close": 66940.0,
        "tick_volume": 234387,
        "spread": 0,
        "real_volume": 0
      },
      {
        "time": "2026-04-03T00:00:00+00:00",
        "open": 66886.0,
        "high": 67387.0,
        "low": 66257.0,
        "close": 66827.0,
        "tick_volume": 149791,
        "spread": 0,
        "real_volume": 0
      },
      {
        "time": "2026-04-06T00:00:00+00:00",
        "open": 67519.0,
        "high": 70370.0,
        "low": 67306.0,
        "close": 69815.0,
        "tick_volume": 212126,
        "spread": 0,
        "real_volume": 0
      },
      {
        "time": "2026-04-07T00:00:00+00:00",
        "open": 69703.0,
        "high": 69773.0,
        "low": 67708.0,
        "close": 69318.0,
        "tick_volume": 203048,
        "spread": 0,
        "real_volume": 0
      },
      {
        "time": "2026-04-08T00:00:00+00:00",
        "open": 69292.0,
        "high": 72756.0,
        "low": 69292.0,
        "close": 71519.0,
        "tick_volume": 69534,
        "spread": 0,
        "real_volume": 0
      }
    ],
    "week": [
      {
        "time": "2025-09-14T00:00:00+00:00",
        "open": 115893.5,
        "high": 117983.0,
        "low": 114412.5,
        "close": 115380.0,
        "tick_volume": 1116133,
        "spread": 0,
        "real_volume": 0
      },
      {
        "time": "2025-09-21T00:00:00+00:00",
        "open": 115343.0,
        "high": 115621.0,
        "low": 108650.0,
        "close": 109354.0,
        "tick_volume": 1168741,
        "spread": 0,
        "real_volume": 0
      },
      {
        "time": "2025-09-28T00:00:00+00:00",
        "open": 110763.0,
        "high": 123996.0,
        "low": 110665.0,
        "close": 122558.0,
        "tick_volume": 1366674,
        "spread": 0,
        "real_volume": 0
      },
      {
        "time": "2025-10-05T00:00:00+00:00",
        "open": 122644.86,
        "high": 126301.0,
        "low": 113000.0,
        "close": 114271.28,
        "tick_volume": 1771701,
        "spread": 0,
        "real_volume": 0
      },
      {
        "time": "2025-10-12T00:00:00+00:00",
        "open": 115134.0,
        "high": 116059.5,
        "low": 103471.53,
        "close": 106965.3,
        "tick_volume": 2692690,
        "spread": 0,
        "real_volume": 0
      },
      {
        "time": "2025-10-19T00:00:00+00:00",
        "open": 108865.62,
        "high": 114077.7,
        "low": 106594.44,
        "close": 110905.1,
        "tick_volume": 2156155,
        "spread": 0,
        "real_volume": 0
      },
      {
        "time": "2025-10-26T00:00:00+00:00",
        "open": 113392.69,
        "high": 116396.99,
        "low": 106254.4,
        "close": 109389.8,
        "tick_volume": 2198256,
        "spread": 0,
        "real_volume": 0
      },
      {
        "time": "2025-11-02T00:00:00+00:00",
        "open": 109960.0,
        "high": 110748.3,
        "low": 98882.4,
        "close": 103865.1,
        "tick_volume": 2973548,
        "spread": 0,
        "real_volume": 0
      },
      {
        "time": "2025-11-09T00:00:00+00:00",
        "open": 104387.26,
        "high": 107506.5,
        "low": 94095.0,
        "close": 94986.0,
        "tick_volume": 2341488,
        "spread": 0,
        "real_volume": 0
      },
      {
        "time": "2025-11-16T00:00:00+00:00",
        "open": 93106.0,
        "high": 95969.0,
        "low": 80531.0,
        "close": 85109.0,
        "tick_volume": 2663415,
        "spread": 0,
        "real_volume": 0
      },
      {
        "time": "2025-11-23T00:00:00+00:00",
        "open": 87787.0,
        "high": 93060.0,
        "low": 85211.0,
        "close": 90910.0,
        "tick_volume": 1656187,
        "spread": 0,
        "real_volume": 0
      },
      {
        "time": "2025-11-30T00:00:00+00:00",
        "open": 91270.0,
        "high": 94185.0,
        "low": 83787.0,
        "close": 89166.0,
        "tick_volume": 1709926,
        "spread": 0,
        "real_volume": 0
      },
      {
        "time": "2025-12-07T00:00:00+00:00",
        "open": 89936.0,
        "high": 94628.0,
        "low": 88938.0,
        "close": 90206.0,
        "tick_volume": 1383431,
        "spread": 0,
        "real_volume": 0
      },
      {
        "time": "2025-12-14T00:00:00+00:00",
        "open": 88528.0,
        "high": 90339.0,
        "low": 84386.0,
        "close": 87646.0,
        "tick_volume": 1397209,
        "spread": 0,
        "real_volume": 0
      },
      {
        "time": "2025-12-21T00:00:00+00:00",
        "open": 88165.0,
        "high": 90555.0,
        "low": 86340.0,
        "close": 87405.0,
        "tick_volume": 1063148,
        "spread": 0,
        "real_volume": 0
      },
      {
        "time": "2025-12-28T00:00:00+00:00",
        "open": 87431.0,
        "high": 90957.0,
        "low": 86662.0,
        "close": 90011.0,
        "tick_volume": 815035,
        "spread": 0,
        "real_volume": 0
      },
      {
        "time": "2026-01-04T00:00:00+00:00",
        "open": 91289.0,
        "high": 94821.0,
        "low": 89172.0,
        "close": 90408.0,
        "tick_volume": 1146754,
        "spread": 0,
        "real_volume": 0
      },
      {
        "time": "2026-01-11T00:00:00+00:00",
        "open": 90350.0,
        "high": 97961.0,
        "low": 89982.0,
        "close": 95481.0,
        "tick_volume": 1041461,
        "spread": 0,
        "real_volume": 0
      },
      {
        "time": "2026-01-18T00:00:00+00:00",
        "open": 95391.0,
        "high": 95520.0,
        "low": 87129.0,
        "close": 89236.0,
        "tick_volume": 1220564,
        "spread": 0,
        "real_volume": 0
      },
      {
        "time": "2026-01-25T00:00:00+00:00",
        "open": 86351.0,
        "high": 90471.0,
        "low": 81000.0,
        "close": 83992.0,
        "tick_volume": 1359537,
        "spread": 0,
        "real_volume": 0
      },
      {
        "time": "2026-02-01T00:00:00+00:00",
        "open": 76829.0,
        "high": 79306.0,
        "low": 59787.0,
        "close": 70330.0,
        "tick_volume": 2212484,
        "spread": 0,
        "real_volume": 0
      },
      {
        "time": "2026-02-08T00:00:00+00:00",
        "open": 70731.0,
        "high": 72210.0,
        "low": 65068.0,
        "close": 68855.0,
        "tick_volume": 1792625,
        "spread": 0,
        "real_volume": 0
      },
      {
        "time": "2026-02-15T00:00:00+00:00",
        "open": 68886.0,
        "high": 70109.0,
        "low": 65575.0,
        "close": 67804.0,
        "tick_volume": 1521147,
        "spread": 0,
        "real_volume": 0
      },
      {
        "time": "2026-02-22T00:00:00+00:00",
        "open": 67526.0,
        "high": 70011.0,
        "low": 62475.0,
        "close": 65542.0,
        "tick_volume": 1511762,
        "spread": 0,
        "real_volume": 0
      },
      {
        "time": "2026-03-01T00:00:00+00:00",
        "open": 65712.0,
        "high": 74082.0,
        "low": 65010.0,
        "close": 68319.0,
        "tick_volume": 1705021,
        "spread": 0,
        "real_volume": 0
      },
      {
        "time": "2026-03-08T00:00:00+00:00",
        "open": 67216.0,
        "high": 73941.0,
        "low": 65579.0,
        "close": 71364.0,
        "tick_volume": 1490400,
        "spread": 0,
        "real_volume": 0
      },
      {
        "time": "2026-03-15T00:00:00+00:00",
        "open": 71682.0,
        "high": 76006.0,
        "low": 68731.0,
        "close": 70040.0,
        "tick_volume": 1336556,
        "spread": 0,
        "real_volume": 0
      },
      {
        "time": "2026-03-22T00:00:00+00:00",
        "open": 68032.0,
        "high": 72035.0,
        "low": 65482.0,
        "close": 65972.0,
        "tick_volume": 1314579,
        "spread": 0,
        "real_volume": 0
      },
      {
        "time": "2026-03-29T00:00:00+00:00",
        "open": 66497.0,
        "high": 69271.0,
        "low": 64920.0,
        "close": 66827.0,
        "tick_volume": 1099281,
        "spread": 0,
        "real_volume": 0
      },
      {
        "time": "2026-04-05T00:00:00+00:00",
        "open": 67519.0,
        "high": 72756.0,
        "low": 67306.0,
        "close": 71519.0,
        "tick_volume": 484708,
        "spread": 0,
        "real_volume": 0
      }
    ],
    "month": [
      {
        "time": "2024-05-01T00:00:00+00:00",
        "open": 59991.79,
        "high": 71954.89,
        "low": 56483.86,
        "close": 67630.88,
        "tick_volume": 8745118,
        "spread": 0,
        "real_volume": 0
      },
      {
        "time": "2024-06-01T00:00:00+00:00",
        "open": 67762.92,
        "high": 71950.14,
        "low": 58398.53,
        "close": 60079.52,
        "tick_volume": 5517034,
        "spread": 0,
        "real_volume": 0
      },
      {
        "time": "2024-07-01T00:00:00+00:00",
        "open": 61862.46,
        "high": 70025.09,
        "low": 53418.55,
        "close": 64558.54,
        "tick_volume": 8006546,
        "spread": 0,
        "real_volume": 0
      },
      {
        "time": "2024-08-01T00:00:00+00:00",
        "open": 64585.47,
        "high": 65604.75,
        "low": 48814.14,
        "close": 59040.95,
        "tick_volume": 7301799,
        "spread": 0,
        "real_volume": 0
      },
      {
        "time": "2024-09-01T00:00:00+00:00",
        "open": 58383.25,
        "high": 66503.95,
        "low": 52613.81,
        "close": 63796.73,
        "tick_volume": 4247359,
        "spread": 1,
        "real_volume": 0
      },
      {
        "time": "2024-10-01T00:00:00+00:00",
        "open": 63752.72,
        "high": 73619.16,
        "low": 58856.22,
        "close": 69857.28,
        "tick_volume": 4467202,
        "spread": 1,
        "real_volume": 0
      },
      {
        "time": "2024-11-01T00:00:00+00:00",
        "open": 69792.51,
        "high": 99815.97,
        "low": 66770.97,
        "close": 97498.39,
        "tick_volume": 6611747,
        "spread": 1,
        "real_volume": 0
      },
      {
        "time": "2024-12-01T00:00:00+00:00",
        "open": 97793.9,
        "high": 108408.47,
        "low": 91280.58,
        "close": 93628.91,
        "tick_volume": 6062199,
        "spread": 1,
        "real_volume": 0
      },
      {
        "time": "2025-01-01T00:00:00+00:00",
        "open": 93713.8,
        "high": 109586.7,
        "low": 89063.37,
        "close": 102157.4,
        "tick_volume": 6432159,
        "spread": 1,
        "real_volume": 0
      },
      {
        "time": "2025-02-01T00:00:00+00:00",
        "open": 97432.54,
        "high": 102593.53,
        "low": 78116.83,
        "close": 84175.78,
        "tick_volume": 4997511,
        "spread": 1,
        "real_volume": 0
      },
      {
        "time": "2025-03-01T00:00:00+00:00",
        "open": 94084.76,
        "high": 94877.8,
        "low": 76555.03,
        "close": 82436.41,
        "tick_volume": 5943297,
        "spread": 1,
        "real_volume": 0
      },
      {
        "time": "2025-04-01T00:00:00+00:00",
        "open": 82534.74,
        "high": 95881.32,
        "low": 74394.34,
        "close": 94547.01,
        "tick_volume": 6108301,
        "spread": 1,
        "real_volume": 0
      },
      {
        "time": "2025-05-01T00:00:00+00:00",
        "open": 94601.52,
        "high": 112031.51,
        "low": 93356.98,
        "close": 104561.03,
        "tick_volume": 6488255,
        "spread": 1,
        "real_volume": 0
      },
      {
        "time": "2025-06-01T00:00:00+00:00",
        "open": 105026.98,
        "high": 110671.73,
        "low": 99011.78,
        "close": 107578.34,
        "tick_volume": 5121986,
        "spread": 1,
        "real_volume": 0
      },
      {
        "time": "2025-07-01T00:00:00+00:00",
        "open": 107491.33,
        "high": 123278.42,
        "low": 105105.68,
        "close": 116482.0,
        "tick_volume": 6709805,
        "spread": 1,
        "real_volume": 0
      },
      {
        "time": "2025-08-01T00:00:00+00:00",
        "open": 116632.25,
        "high": 124562.75,
        "low": 107527.5,
        "close": 107782.75,
        "tick_volume": 6674538,
        "spread": 1,
        "real_volume": 0
      },
      {
        "time": "2025-09-01T00:00:00+00:00",
        "open": 109052.25,
        "high": 117983.0,
        "low": 107254.75,
        "close": 114650.0,
        "tick_volume": 5502411,
        "spread": 0,
        "real_volume": 0
      },
      {
        "time": "2025-10-01T00:00:00+00:00",
        "open": 114717.12,
        "high": 126301.0,
        "low": 103471.53,
        "close": 109389.8,
        "tick_volume": 9650475,
        "spread": 0,
        "real_volume": 0
      },
      {
        "time": "2025-11-01T00:00:00+00:00",
        "open": 109960.0,
        "high": 110748.3,
        "low": 80531.0,
        "close": 90910.0,
        "tick_volume": 9634638,
        "spread": 0,
        "real_volume": 0
      },
      {
        "time": "2025-12-01T00:00:00+00:00",
        "open": 91270.0,
        "high": 94628.0,
        "low": 83787.0,
        "close": 87662.0,
        "tick_volume": 6079086,
        "spread": 0,
        "real_volume": 0
      },
      {
        "time": "2026-01-01T00:00:00+00:00",
        "open": 87469.0,
        "high": 97961.0,
        "low": 81000.0,
        "close": 83992.0,
        "tick_volume": 5057979,
        "spread": 0,
        "real_volume": 0
      },
      {
        "time": "2026-02-01T00:00:00+00:00",
        "open": 76829.0,
        "high": 79306.0,
        "low": 59787.0,
        "close": 65542.0,
        "tick_volume": 7038018,
        "spread": 0,
        "real_volume": 0
      },
      {
        "time": "2026-03-01T00:00:00+00:00",
        "open": 65712.0,
        "high": 76006.0,
        "low": 64920.0,
        "close": 68203.0,
        "tick_volume": 6357823,
        "spread": 0,
        "real_volume": 0
      },
      {
        "time": "2026-04-01T00:00:00+00:00",
        "open": 68007.0,
        "high": 72756.0,
        "low": 65680.0,
        "close": 71519.0,
        "tick_volume": 1072722,
        "spread": 0,
        "real_volume": 0
      }
    ]
  },
  "oscillators": {
    "1h": {
      "rsi": [
        {
          "time": "2026-04-07T11:00:00+00:00",
          "value": 33.707865
        },
        {
          "time": "2026-04-07T12:00:00+00:00",
          "value": 38.36357
        },
        {
          "time": "2026-04-07T13:00:00+00:00",
          "value": 28.708642
        },
        {
          "time": "2026-04-07T14:00:00+00:00",
          "value": 30.717588
        },
        {
          "time": "2026-04-07T15:00:00+00:00",
          "value": 32.022694
        },
        {
          "time": "2026-04-07T16:00:00+00:00",
          "value": 30.344719
        },
        {
          "time": "2026-04-07T17:00:00+00:00",
          "value": 26.919995
        },
        {
          "time": "2026-04-07T18:00:00+00:00",
          "value": 33.47737
        },
        {
          "time": "2026-04-07T19:00:00+00:00",
          "value": 34.981978
        },
        {
          "time": "2026-04-07T20:00:00+00:00",
          "value": 43.660842
        },
        {
          "time": "2026-04-07T21:00:00+00:00",
          "value": 40.420366
        },
        {
          "time": "2026-04-07T22:00:00+00:00",
          "value": 49.142176
        },
        {
          "time": "2026-04-07T23:00:00+00:00",
          "value": 53.393255
        },
        {
          "time": "2026-04-08T00:00:00+00:00",
          "value": 60.05246
        },
        {
          "time": "2026-04-08T01:00:00+00:00",
          "value": 71.628491
        },
        {
          "time": "2026-04-08T02:00:00+00:00",
          "value": 73.716455
        }
      ],
      "ma": [
        {
          "time": "2026-04-07T16:00:00+00:00",
          "value": 68859.45
        },
        {
          "time": "2026-04-07T17:00:00+00:00",
          "value": 68756.6
        },
        {
          "time": "2026-04-07T18:00:00+00:00",
          "value": 68679.35
        },
        {
          "time": "2026-04-07T19:00:00+00:00",
          "value": 68599.95
        },
        {
          "time": "2026-04-07T20:00:00+00:00",
          "value": 68558.75
        },
        {
          "time": "2026-04-07T21:00:00+00:00",
          "value": 68540.05
        },
        {
          "time": "2026-04-07T22:00:00+00:00",
          "value": 68547.25
        },
        {
          "time": "2026-04-07T23:00:00+00:00",
          "value": 68574.5
        },
        {
          "time": "2026-04-08T00:00:00+00:00",
          "value": 68650.15
        },
        {
          "time": "2026-04-08T01:00:00+00:00",
          "value": 68792.55
        },
        {
          "time": "2026-04-08T02:00:00+00:00",
          "value": 68949.65
        }
      ]
    },
    "4h": {
      "rsi": [
        {
          "time": "2026-04-03T12:00:00+00:00",
          "value": 39.108135
        },
        {
          "time": "2026-04-03T16:00:00+00:00",
          "value": 41.487199
        },
        {
          "time": "2026-04-03T20:00:00+00:00",
          "value": 40.390565
        },
        {
          "time": "2026-04-06T00:00:00+00:00",
          "value": 56.575885
        },
        {
          "time": "2026-04-06T04:00:00+00:00",
          "value": 56.874388
        },
        {
          "time": "2026-04-06T08:00:00+00:00",
          "value": 57.456736
        },
        {
          "time": "2026-04-06T12:00:00+00:00",
          "value": 58.437369
        },
        {
          "time": "2026-04-06T16:00:00+00:00",
          "value": 61.142991
        },
        {
          "time": "2026-04-06T20:00:00+00:00",
          "value": 61.075789
        },
        {
          "time": "2026-04-07T00:00:00+00:00",
          "value": 51.92667
        },
        {
          "time": "2026-04-07T04:00:00+00:00",
          "value": 52.551084
        },
        {
          "time": "2026-04-07T08:00:00+00:00",
          "value": 53.213232
        },
        {
          "time": "2026-04-07T12:00:00+00:00",
          "value": 48.547254
        },
        {
          "time": "2026-04-07T16:00:00+00:00",
          "value": 47.194094
        },
        {
          "time": "2026-04-07T20:00:00+00:00",
          "value": 55.851594
        },
        {
          "time": "2026-04-08T00:00:00+00:00",
          "value": 68.168603
        }
      ],
      "ma": [
        {
          "time": "2026-04-06T08:00:00+00:00",
          "value": 67599.8
        },
        {
          "time": "2026-04-06T12:00:00+00:00",
          "value": 67655.5
        },
        {
          "time": "2026-04-06T16:00:00+00:00",
          "value": 67714.1
        },
        {
          "time": "2026-04-06T20:00:00+00:00",
          "value": 67786.2
        },
        {
          "time": "2026-04-07T00:00:00+00:00",
          "value": 67784.95
        },
        {
          "time": "2026-04-07T04:00:00+00:00",
          "value": 67818.15
        },
        {
          "time": "2026-04-07T08:00:00+00:00",
          "value": 67835.4
        },
        {
          "time": "2026-04-07T12:00:00+00:00",
          "value": 67939.4
        },
        {
          "time": "2026-04-07T16:00:00+00:00",
          "value": 68029.4
        },
        {
          "time": "2026-04-07T20:00:00+00:00",
          "value": 68193.9
        },
        {
          "time": "2026-04-08T00:00:00+00:00",
          "value": 68425.15
        }
      ]
    },
    "day": {
      "rsi": [
        {
          "time": "2026-03-18T00:00:00+00:00",
          "value": 56.692181
        },
        {
          "time": "2026-03-19T00:00:00+00:00",
          "value": 55.090048
        },
        {
          "time": "2026-03-20T00:00:00+00:00",
          "value": 54.157862
        },
        {
          "time": "2026-03-23T00:00:00+00:00",
          "value": 55.747987
        },
        {
          "time": "2026-03-24T00:00:00+00:00",
          "value": 53.793413
        },
        {
          "time": "2026-03-25T00:00:00+00:00",
          "value": 55.675448
        },
        {
          "time": "2026-03-26T00:00:00+00:00",
          "value": 50.776004
        },
        {
          "time": "2026-03-27T00:00:00+00:00",
          "value": 44.553062
        },
        {
          "time": "2026-03-30T00:00:00+00:00",
          "value": 45.85266
        },
        {
          "time": "2026-03-31T00:00:00+00:00",
          "value": 49.792322
        },
        {
          "time": "2026-04-01T00:00:00+00:00",
          "value": 49.771529
        },
        {
          "time": "2026-04-02T00:00:00+00:00",
          "value": 46.83671
        },
        {
          "time": "2026-04-03T00:00:00+00:00",
          "value": 46.570224
        },
        {
          "time": "2026-04-06T00:00:00+00:00",
          "value": 54.020006
        },
        {
          "time": "2026-04-07T00:00:00+00:00",
          "value": 52.703685
        },
        {
          "time": "2026-04-08T00:00:00+00:00",
          "value": 57.627883
        }
      ],
      "ma": [
        {
          "time": "2026-03-25T00:00:00+00:00",
          "value": 70356.35
        },
        {
          "time": "2026-03-26T00:00:00+00:00",
          "value": 70430.25
        },
        {
          "time": "2026-03-27T00:00:00+00:00",
          "value": 70451.75
        },
        {
          "time": "2026-03-30T00:00:00+00:00",
          "value": 70305.55
        },
        {
          "time": "2026-03-31T00:00:00+00:00",
          "value": 70313.85
        },
        {
          "time": "2026-04-01T00:00:00+00:00",
          "value": 70056.0
        },
        {
          "time": "2026-04-02T00:00:00+00:00",
          "value": 69845.7
        },
        {
          "time": "2026-04-03T00:00:00+00:00",
          "value": 69771.1
        },
        {
          "time": "2026-04-06T00:00:00+00:00",
          "value": 69813.65
        },
        {
          "time": "2026-04-07T00:00:00+00:00",
          "value": 69766.45
        },
        {
          "time": "2026-04-08T00:00:00+00:00",
          "value": 69811.9
        }
      ]
    },
    "week": {
      "rsi": [
        {
          "time": "2025-12-21T00:00:00+00:00",
          "value": 31.581969
        },
        {
          "time": "2025-12-28T00:00:00+00:00",
          "value": 34.020191
        },
        {
          "time": "2026-01-04T00:00:00+00:00",
          "value": 34.403706
        },
        {
          "time": "2026-01-11T00:00:00+00:00",
          "value": 39.262077
        },
        {
          "time": "2026-01-18T00:00:00+00:00",
          "value": 35.751652
        },
        {
          "time": "2026-01-25T00:00:00+00:00",
          "value": 33.077227
        },
        {
          "time": "2026-02-01T00:00:00+00:00",
          "value": 27.339267
        },
        {
          "time": "2026-02-08T00:00:00+00:00",
          "value": 26.798754
        },
        {
          "time": "2026-02-15T00:00:00+00:00",
          "value": 26.398266
        },
        {
          "time": "2026-02-22T00:00:00+00:00",
          "value": 25.514502
        },
        {
          "time": "2026-03-01T00:00:00+00:00",
          "value": 28.671624
        },
        {
          "time": "2026-03-08T00:00:00+00:00",
          "value": 32.071535
        },
        {
          "time": "2026-03-15T00:00:00+00:00",
          "value": 31.371332
        },
        {
          "time": "2026-03-22T00:00:00+00:00",
          "value": 29.257736
        },
        {
          "time": "2026-03-29T00:00:00+00:00",
          "value": 30.320324
        },
        {
          "time": "2026-04-05T00:00:00+00:00",
          "value": 36.001432
        }
      ],
      "ma": [
        {
          "time": "2026-01-25T00:00:00+00:00",
          "value": 98362.229
        },
        {
          "time": "2026-02-01T00:00:00+00:00",
          "value": 96109.729
        },
        {
          "time": "2026-02-08T00:00:00+00:00",
          "value": 94084.779
        },
        {
          "time": "2026-02-15T00:00:00+00:00",
          "value": 91347.079
        },
        {
          "time": "2026-02-22T00:00:00+00:00",
          "value": 88910.615
        },
        {
          "time": "2026-03-01T00:00:00+00:00",
          "value": 86978.3
        },
        {
          "time": "2026-03-08T00:00:00+00:00",
          "value": 85001.245
        },
        {
          "time": "2026-03-15T00:00:00+00:00",
          "value": 83033.755
        },
        {
          "time": "2026-03-22T00:00:00+00:00",
          "value": 81139.1
        },
        {
          "time": "2026-03-29T00:00:00+00:00",
          "value": 79731.15
        },
        {
          "time": "2026-04-05T00:00:00+00:00",
          "value": 79051.65
        }
      ]
    },
    "month": {
      "rsi": [
        {
          "time": "2025-07-01T00:00:00+00:00",
          "value": 69.993098
        },
        {
          "time": "2025-08-01T00:00:00+00:00",
          "value": 65.008052
        },
        {
          "time": "2025-09-01T00:00:00+00:00",
          "value": 67.005785
        },
        {
          "time": "2025-10-01T00:00:00+00:00",
          "value": 63.992087
        },
        {
          "time": "2025-11-01T00:00:00+00:00",
          "value": 54.686436
        },
        {
          "time": "2025-12-01T00:00:00+00:00",
          "value": 53.221525
        },
        {
          "time": "2026-01-01T00:00:00+00:00",
          "value": 51.541471
        },
        {
          "time": "2026-02-01T00:00:00+00:00",
          "value": 44.018549
        },
        {
          "time": "2026-03-01T00:00:00+00:00",
          "value": 45.259548
        },
        {
          "time": "2026-04-01T00:00:00+00:00",
          "value": 46.841008
        }
      ],
      "ma": [
        {
          "time": "2025-12-01T00:00:00+00:00",
          "value": 88921.186
        },
        {
          "time": "2026-01-01T00:00:00+00:00",
          "value": 89739.242
        },
        {
          "time": "2026-02-01T00:00:00+00:00",
          "value": 90012.366
        },
        {
          "time": "2026-03-01T00:00:00+00:00",
          "value": 90194.589
        },
        {
          "time": "2026-04-01T00:00:00+00:00",
          "value": 90818.4915
        }
      ]
    }
  }
}