{
  "symbol": "EURMXN_ecn",
  "generated_at": "2026-03-19T16:22:59.185054+00:00",
  "lookback_periods": 30,
  "current_price": 20.56393,
  "candles": {
    "1h": [
      {
        "time": "2026-03-18T11:00:00+00:00",
        "open": 20.31217,
        "high": 20.32463,
        "low": 20.30599,
        "close": 20.30939,
        "tick_volume": 6740,
        "spread": 66,
        "real_volume": 0
      },
      {
        "time": "2026-03-18T12:00:00+00:00",
        "open": 20.30939,
        "high": 20.3153,
        "low": 20.30158,
        "close": 20.31439,
        "tick_volume": 5524,
        "spread": 107,
        "real_volume": 0
      },
      {
        "time": "2026-03-18T13:00:00+00:00",
        "open": 20.31457,
        "high": 20.34313,
        "low": 20.3105,
        "close": 20.3412,
        "tick_volume": 4057,
        "spread": 25,
        "real_volume": 0
      },
      {
        "time": "2026-03-18T14:00:00+00:00",
        "open": 20.34123,
        "high": 20.35429,
        "low": 20.33254,
        "close": 20.34234,
        "tick_volume": 9392,
        "spread": 25,
        "real_volume": 0
      },
      {
        "time": "2026-03-18T15:00:00+00:00",
        "open": 20.34234,
        "high": 20.41826,
        "low": 20.33895,
        "close": 20.41777,
        "tick_volume": 14590,
        "spread": 22,
        "real_volume": 0
      },
      {
        "time": "2026-03-18T16:00:00+00:00",
        "open": 20.41777,
        "high": 20.42407,
        "low": 20.37833,
        "close": 20.3854,
        "tick_volume": 15484,
        "spread": 3,
        "real_volume": 0
      },
      {
        "time": "2026-03-18T17:00:00+00:00",
        "open": 20.3854,
        "high": 20.39842,
        "low": 20.3472,
        "close": 20.35164,
        "tick_volume": 13400,
        "spread": 3,
        "real_volume": 0
      },
      {
        "time": "2026-03-18T18:00:00+00:00",
        "open": 20.35164,
        "high": 20.36116,
        "low": 20.3315,
        "close": 20.3527,
        "tick_volume": 10798,
        "spread": 6,
        "real_volume": 0
      },
      {
        "time": "2026-03-18T19:00:00+00:00",
        "open": 20.3527,
        "high": 20.36808,
        "low": 20.32549,
        "close": 20.35254,
        "tick_volume": 7457,
        "spread": 35,
        "real_volume": 0
      },
      {
        "time": "2026-03-18T20:00:00+00:00",
        "open": 20.35262,
        "high": 20.38121,
        "low": 20.34859,
        "close": 20.367,
        "tick_volume": 6541,
        "spread": 61,
        "real_volume": 0
      },
      {
        "time": "2026-03-18T21:00:00+00:00",
        "open": 20.36635,
        "high": 20.41968,
        "low": 20.35923,
        "close": 20.38746,
        "tick_volume": 15677,
        "spread": 3,
        "real_volume": 0
      },
      {
        "time": "2026-03-18T22:00:00+00:00",
        "open": 20.3873,
        "high": 20.45237,
        "low": 20.38679,
        "close": 20.43717,
        "tick_volume": 10293,
        "spread": 0,
        "real_volume": 0
      },
      {
        "time": "2026-03-18T23:00:00+00:00",
        "open": 20.43696,
        "high": 20.47089,
        "low": 20.43203,
        "close": 20.44406,
        "tick_volume": 6718,
        "spread": 2,
        "real_volume": 0
      },
      {
        "time": "2026-03-19T00:00:00+00:00",
        "open": 20.44475,
        "high": 20.46349,
        "low": 20.42046,
        "close": 20.42828,
        "tick_volume": 2742,
        "spread": 1554,
        "real_volume": 0
      },
      {
        "time": "2026-03-19T01:00:00+00:00",
        "open": 20.42828,
        "high": 20.46846,
        "low": 20.42341,
        "close": 20.4635,
        "tick_volume": 4304,
        "spread": 146,
        "real_volume": 0
      },
      {
        "time": "2026-03-19T02:00:00+00:00",
        "open": 20.4635,
        "high": 20.47506,
        "low": 20.46049,
        "close": 20.4676,
        "tick_volume": 4483,
        "spread": 200,
        "real_volume": 0
      },
      {
        "time": "2026-03-19T03:00:00+00:00",
        "open": 20.46796,
        "high": 20.47125,
        "low": 20.44733,
        "close": 20.45068,
        "tick_volume": 5917,
        "spread": 326,
        "real_volume": 0
      },
      {
        "time": "2026-03-19T04:00:00+00:00",
        "open": 20.4507,
        "high": 20.45752,
        "low": 20.44154,
        "close": 20.44896,
        "tick_volume": 5489,
        "spread": 314,
        "real_volume": 0
      },
      {
        "time": "2026-03-19T05:00:00+00:00",
        "open": 20.44914,
        "high": 20.45417,
        "low": 20.4352,
        "close": 20.43945,
        "tick_volume": 5787,
        "spread": 210,
        "real_volume": 0
      },
      {
        "time": "2026-03-19T06:00:00+00:00",
        "open": 20.43956,
        "high": 20.44125,
        "low": 20.42564,
        "close": 20.42839,
        "tick_volume": 3069,
        "spread": 314,
        "real_volume": 0
      },
      {
        "time": "2026-03-19T07:00:00+00:00",
        "open": 20.42796,
        "high": 20.43946,
        "low": 20.42796,
        "close": 20.4348,
        "tick_volume": 2580,
        "spread": 430,
        "real_volume": 0
      },
      {
        "time": "2026-03-19T08:00:00+00:00",
        "open": 20.43467,
        "high": 20.44163,
        "low": 20.42312,
        "close": 20.43642,
        "tick_volume": 5211,
        "spread": 381,
        "real_volume": 0
      },
      {
        "time": "2026-03-19T09:00:00+00:00",
        "open": 20.43642,
        "high": 20.4426,
        "low": 20.41878,
        "close": 20.43189,
        "tick_volume": 7674,
        "spread": 136,
        "real_volume": 0
      },
      {
        "time": "2026-03-19T10:00:00+00:00",
        "open": 20.43189,
        "high": 20.46234,
        "low": 20.42823,
        "close": 20.45023,
        "tick_volume": 13054,
        "spread": 130,
        "real_volume": 0
      },
      {
        "time": "2026-03-19T11:00:00+00:00",
        "open": 20.45023,
        "high": 20.45307,
        "low": 20.4261,
        "close": 20.43136,
        "tick_volume": 14030,
        "spread": 36,
        "real_volume": 0
      },
      {
        "time": "2026-03-19T12:00:00+00:00",
        "open": 20.43136,
        "high": 20.45462,
        "low": 20.41264,
        "close": 20.41712,
        "tick_volume": 15732,
        "spread": 4,
        "real_volume": 0
      },
      {
        "time": "2026-03-19T13:00:00+00:00",
        "open": 20.41712,
        "high": 20.42448,
        "low": 20.4065,
        "close": 20.41532,
        "tick_volume": 11258,
        "spread": 37,
        "real_volume": 0
      },
      {
        "time": "2026-03-19T14:00:00+00:00",
        "open": 20.41531,
        "high": 20.44377,
        "low": 20.41165,
        "close": 20.42663,
        "tick_volume": 9544,
        "spread": 11,
        "real_volume": 0
      },
      {
        "time": "2026-03-19T15:00:00+00:00",
        "open": 20.42663,
        "high": 20.51912,
        "low": 20.42663,
        "close": 20.51572,
        "tick_volume": 16345,
        "spread": 1,
        "real_volume": 0
      },
      {
        "time": "2026-03-19T16:00:00+00:00",
        "open": 20.5155,
        "high": 20.63444,
        "low": 20.50904,
        "close": 20.56676,
        "tick_volume": 19146,
        "spread": 1,
        "real_volume": 0
      }
    ],
    "4h": [
      {
        "time": "2026-03-12T20:00:00+00:00",
        "open": 20.53613,
        "high": 20.57249,
        "low": 20.51635,
        "close": 20.55549,
        "tick_volume": 31683,
        "spread": 2,
        "real_volume": 0
      },
      {
        "time": "2026-03-13T00:00:00+00:00",
        "open": 20.51065,
        "high": 20.57238,
        "low": 20.508,
        "close": 20.53363,
        "tick_volume": 12681,
        "spread": 39,
        "real_volume": 0
      },
      {
        "time": "2026-03-13T04:00:00+00:00",
        "open": 20.53363,
        "high": 20.53454,
        "low": 20.50255,
        "close": 20.52059,
        "tick_volume": 16672,
        "spread": 249,
        "real_volume": 0
      },
      {
        "time": "2026-03-13T08:00:00+00:00",
        "open": 20.52094,
        "high": 20.55059,
        "low": 20.4865,
        "close": 20.48935,
        "tick_volume": 32421,
        "spread": 0,
        "real_volume": 0
      },
      {
        "time": "2026-03-13T12:00:00+00:00",
        "open": 20.48935,
        "high": 20.50434,
        "low": 20.42352,
        "close": 20.42656,
        "tick_volume": 42918,
        "spread": 10,
        "real_volume": 0
      },
      {
        "time": "2026-03-13T16:00:00+00:00",
        "open": 20.42679,
        "high": 20.55909,
        "low": 20.37941,
        "close": 20.48681,
        "tick_volume": 59636,
        "spread": 0,
        "real_volume": 0
      },
      {
        "time": "2026-03-13T20:00:00+00:00",
        "open": 20.48716,
        "high": 20.52423,
        "low": 20.44507,
        "close": 20.48049,
        "tick_volume": 32084,
        "spread": 1,
        "real_volume": 0
      },
      {
        "time": "2026-03-16T00:00:00+00:00",
        "open": 20.44119,
        "high": 20.51049,
        "low": 20.34984,
        "close": 20.4297,
        "tick_volume": 17377,
        "spread": 11,
        "real_volume": 0
      },
      {
        "time": "2026-03-16T04:00:00+00:00",
        "open": 20.42965,
        "high": 20.44741,
        "low": 20.41699,
        "close": 20.44061,
        "tick_volume": 18081,
        "spread": 214,
        "real_volume": 0
      },
      {
        "time": "2026-03-16T08:00:00+00:00",
        "open": 20.44061,
        "high": 20.46446,
        "low": 20.39449,
        "close": 20.45052,
        "tick_volume": 29162,
        "spread": 48,
        "real_volume": 0
      },
      {
        "time": "2026-03-16T12:00:00+00:00",
        "open": 20.45047,
        "high": 20.46429,
        "low": 20.41185,
        "close": 20.43231,
        "tick_volume": 38216,
        "spread": 1,
        "real_volume": 0
      },
      {
        "time": "2026-03-16T16:00:00+00:00",
        "open": 20.43245,
        "high": 20.46024,
        "low": 20.38661,
        "close": 20.40142,
        "tick_volume": 43470,
        "spread": 0,
        "real_volume": 0
      },
      {
        "time": "2026-03-16T20:00:00+00:00",
        "open": 20.40147,
        "high": 20.40147,
        "low": 20.33774,
        "close": 20.34105,
        "tick_volume": 24432,
        "spread": 3,
        "real_volume": 0
      },
      {
        "time": "2026-03-17T00:00:00+00:00",
        "open": 20.34105,
        "high": 20.36421,
        "low": 20.3237,
        "close": 20.34447,
        "tick_volume": 13172,
        "spread": 179,
        "real_volume": 0
      },
      {
        "time": "2026-03-17T04:00:00+00:00",
        "open": 20.3446,
        "high": 20.34871,
        "low": 20.32629,
        "close": 20.33041,
        "tick_volume": 17923,
        "spread": 348,
        "real_volume": 0
      },
      {
        "time": "2026-03-17T08:00:00+00:00",
        "open": 20.33041,
        "high": 20.37155,
        "low": 20.31834,
        "close": 20.35445,
        "tick_volume": 31771,
        "spread": 61,
        "real_volume": 0
      },
      {
        "time": "2026-03-17T12:00:00+00:00",
        "open": 20.35445,
        "high": 20.36662,
        "low": 20.324089999999998,
        "close": 20.36662,
        "tick_volume": 31023,
        "spread": 4,
        "real_volume": 0
      },
      {
        "time": "2026-03-17T16:00:00+00:00",
        "open": 20.36642,
        "high": 20.44736,
        "low": 20.32131,
        "close": 20.39962,
        "tick_volume": 46579,
        "spread": 1,
        "real_volume": 0
      },
      {
        "time": "2026-03-17T20:00:00+00:00",
        "open": 20.39946,
        "high": 20.41585,
        "low": 20.3626,
        "close": 20.36978,
        "tick_volume": 17569,
        "spread": 3,
        "real_volume": 0
      },
      {
        "time": "2026-03-18T00:00:00+00:00",
        "open": 20.36978,
        "high": 20.37711,
        "low": 20.35088,
        "close": 20.35165,
        "tick_volume": 12445,
        "spread": 208,
        "real_volume": 0
      },
      {
        "time": "2026-03-18T04:00:00+00:00",
        "open": 20.35155,
        "high": 20.35629,
        "low": 20.34099,
        "close": 20.35115,
        "tick_volume": 8812,
        "spread": 261,
        "real_volume": 0
      },
      {
        "time": "2026-03-18T08:00:00+00:00",
        "open": 20.35115,
        "high": 20.35694,
        "low": 20.30599,
        "close": 20.30939,
        "tick_volume": 18653,
        "spread": 66,
        "real_volume": 0
      },
      {
        "time": "2026-03-18T12:00:00+00:00",
        "open": 20.30939,
        "high": 20.41826,
        "low": 20.30158,
        "close": 20.41777,
        "tick_volume": 33563,
        "spread": 22,
        "real_volume": 0
      },
      {
        "time": "2026-03-18T16:00:00+00:00",
        "open": 20.41777,
        "high": 20.42407,
        "low": 20.32549,
        "close": 20.35254,
        "tick_volume": 47139,
        "spread": 3,
        "real_volume": 0
      },
      {
        "time": "2026-03-18T20:00:00+00:00",
        "open": 20.35262,
        "high": 20.47089,
        "low": 20.34859,
        "close": 20.44406,
        "tick_volume": 39229,
        "spread": 0,
        "real_volume": 0
      },
      {
        "time": "2026-03-19T00:00:00+00:00",
        "open": 20.44475,
        "high": 20.47506,
        "low": 20.42046,
        "close": 20.45068,
        "tick_volume": 17446,
        "spread": 146,
        "real_volume": 0
      },
      {
        "time": "2026-03-19T04:00:00+00:00",
        "open": 20.4507,
        "high": 20.45752,
        "low": 20.42564,
        "close": 20.4348,
        "tick_volume": 16925,
        "spread": 210,
        "real_volume": 0
      },
      {
        "time": "2026-03-19T08:00:00+00:00",
        "open": 20.43467,
        "high": 20.46234,
        "low": 20.41878,
        "close": 20.43136,
        "tick_volume": 39969,
        "spread": 36,
        "real_volume": 0
      },
      {
        "time": "2026-03-19T12:00:00+00:00",
        "open": 20.43136,
        "high": 20.51912,
        "low": 20.4065,
        "close": 20.51572,
        "tick_volume": 52879,
        "spread": 1,
        "real_volume": 0
      },
      {
        "time": "2026-03-19T16:00:00+00:00",
        "open": 20.5155,
        "high": 20.63444,
        "low": 20.50904,
        "close": 20.56676,
        "tick_volume": 19146,
        "spread": 1,
        "real_volume": 0
      }
    ],
    "day": [
      {
        "time": "2026-02-06T00:00:00+00:00",
        "open": 20.61222,
        "high": 20.67549,
        "low": 20.37945,
        "close": 20.39822,
        "tick_volume": 184513,
        "spread": 4,
        "real_volume": 0
      },
      {
        "time": "2026-02-09T00:00:00+00:00",
        "open": 20.33801,
        "high": 20.52385,
        "low": 20.33801,
        "close": 20.47795,
        "tick_volume": 152129,
        "spread": 0,
        "real_volume": 0
      },
      {
        "time": "2026-02-10T00:00:00+00:00",
        "open": 20.47795,
        "high": 20.56288,
        "low": 20.435670000000002,
        "close": 20.44751,
        "tick_volume": 152268,
        "spread": 0,
        "real_volume": 0
      },
      {
        "time": "2026-02-11T00:00:00+00:00",
        "open": 20.44751,
        "high": 20.49455,
        "low": 20.36802,
        "close": 20.39115,
        "tick_volume": 175643,
        "spread": 1,
        "real_volume": 0
      },
      {
        "time": "2026-02-12T00:00:00+00:00",
        "open": 20.39133,
        "high": 20.47909,
        "low": 20.34656,
        "close": 20.4428,
        "tick_volume": 166199,
        "spread": 5,
        "real_volume": 0
      },
      {
        "time": "2026-02-13T00:00:00+00:00",
        "open": 20.44246,
        "high": 20.45991,
        "low": 20.3431,
        "close": 20.36158,
        "tick_volume": 160766,
        "spread": 0,
        "real_volume": 0
      },
      {
        "time": "2026-02-16T00:00:00+00:00",
        "open": 20.35341,
        "high": 20.38098,
        "low": 20.32765,
        "close": 20.34121,
        "tick_volume": 88618,
        "spread": 15,
        "real_volume": 0
      },
      {
        "time": "2026-02-17T00:00:00+00:00",
        "open": 20.3412,
        "high": 20.37719,
        "low": 20.26859,
        "close": 20.29981,
        "tick_volume": 152634,
        "spread": 1,
        "real_volume": 0
      },
      {
        "time": "2026-02-18T00:00:00+00:00",
        "open": 20.29984,
        "high": 20.31617,
        "low": 20.2218,
        "close": 20.27052,
        "tick_volume": 130399,
        "spread": 2,
        "real_volume": 0
      },
      {
        "time": "2026-02-19T00:00:00+00:00",
        "open": 20.27052,
        "high": 20.3585,
        "low": 20.25472,
        "close": 20.30534,
        "tick_volume": 155533,
        "spread": 2,
        "real_volume": 0
      },
      {
        "time": "2026-02-20T00:00:00+00:00",
        "open": 20.30567,
        "high": 20.32104,
        "low": 20.16592,
        "close": 20.17748,
        "tick_volume": 165190,
        "spread": 0,
        "real_volume": 0
      },
      {
        "time": "2026-02-23T00:00:00+00:00",
        "open": 20.19375,
        "high": 20.39343,
        "low": 20.18669,
        "close": 20.34428,
        "tick_volume": 160874,
        "spread": 2,
        "real_volume": 0
      },
      {
        "time": "2026-02-24T00:00:00+00:00",
        "open": 20.34428,
        "high": 20.37917,
        "low": 20.21105,
        "close": 20.21105,
        "tick_volume": 120197,
        "spread": 0,
        "real_volume": 0
      },
      {
        "time": "2026-02-25T00:00:00+00:00",
        "open": 20.21105,
        "high": 20.30816,
        "low": 20.19455,
        "close": 20.26615,
        "tick_volume": 109806,
        "spread": 3,
        "real_volume": 0
      },
      {
        "time": "2026-02-26T00:00:00+00:00",
        "open": 20.26615,
        "high": 20.36864,
        "low": 20.23775,
        "close": 20.2811,
        "tick_volume": 119381,
        "spread": 1,
        "real_volume": 0
      },
      {
        "time": "2026-02-27T00:00:00+00:00",
        "open": 20.28127,
        "high": 20.37299,
        "low": 20.26187,
        "close": 20.34336,
        "tick_volume": 133410,
        "spread": 0,
        "real_volume": 0
      },
      {
        "time": "2026-03-02T00:00:00+00:00",
        "open": 20.39694,
        "high": 20.40475,
        "low": 20.2075,
        "close": 20.21661,
        "tick_volume": 196960,
        "spread": 0,
        "real_volume": 0
      },
      {
        "time": "2026-03-03T00:00:00+00:00",
        "open": 20.21659,
        "high": 20.62835,
        "low": 20.18315,
        "close": 20.55011,
        "tick_volume": 262015,
        "spread": 0,
        "real_volume": 0
      },
      {
        "time": "2026-03-04T00:00:00+00:00",
        "open": 20.55011,
        "high": 20.5978,
        "low": 20.40176,
        "close": 20.42966,
        "tick_volume": 257686,
        "spread": 0,
        "real_volume": 0
      },
      {
        "time": "2026-03-05T00:00:00+00:00",
        "open": 20.40911,
        "high": 20.61697,
        "low": 20.40751,
        "close": 20.56201,
        "tick_volume": 254880,
        "spread": 0,
        "real_volume": 0
      },
      {
        "time": "2026-03-06T00:00:00+00:00",
        "open": 20.56274,
        "high": 20.69155,
        "low": 20.47441,
        "close": 20.6582,
        "tick_volume": 252577,
        "spread": 0,
        "real_volume": 0
      },
      {
        "time": "2026-03-09T00:00:00+00:00",
        "open": 20.61677,
        "high": 20.76933,
        "low": 20.46221,
        "close": 20.46911,
        "tick_volume": 298712,
        "spread": 4,
        "real_volume": 0
      },
      {
        "time": "2026-03-10T00:00:00+00:00",
        "open": 20.46909,
        "high": 20.55435,
        "low": 20.33698,
        "close": 20.42445,
        "tick_volume": 239511,
        "spread": 0,
        "real_volume": 0
      },
      {
        "time": "2026-03-11T00:00:00+00:00",
        "open": 20.42465,
        "high": 20.48097,
        "low": 20.36548,
        "close": 20.442520000000002,
        "tick_volume": 195734,
        "spread": 0,
        "real_volume": 0
      },
      {
        "time": "2026-03-12T00:00:00+00:00",
        "open": 20.44248,
        "high": 20.60982,
        "low": 20.38455,
        "close": 20.55549,
        "tick_volume": 202439,
        "spread": 0,
        "real_volume": 0
      },
      {
        "time": "2026-03-13T00:00:00+00:00",
        "open": 20.51065,
        "high": 20.57238,
        "low": 20.37941,
        "close": 20.48049,
        "tick_volume": 196412,
        "spread": 0,
        "real_volume": 0
      },
      {
        "time": "2026-03-16T00:00:00+00:00",
        "open": 20.44119,
        "high": 20.51049,
        "low": 20.33774,
        "close": 20.34105,
        "tick_volume": 170738,
        "spread": 0,
        "real_volume": 0
      },
      {
        "time": "2026-03-17T00:00:00+00:00",
        "open": 20.34105,
        "high": 20.44736,
        "low": 20.31834,
        "close": 20.36978,
        "tick_volume": 158037,
        "spread": 1,
        "real_volume": 0
      },
      {
        "time": "2026-03-18T00:00:00+00:00",
        "open": 20.36978,
        "high": 20.47089,
        "low": 20.30158,
        "close": 20.44406,
        "tick_volume": 159841,
        "spread": 0,
        "real_volume": 0
      },
      {
        "time": "2026-03-19T00:00:00+00:00",
        "open": 20.44475,
        "high": 20.63444,
        "low": 20.4065,
        "close": 20.56387,
        "tick_volume": 146366,
        "spread": 1,
        "real_volume": 0
      }
    ],
    "week": [
      {
        "time": "2025-08-24T00:00:00+00:00",
        "open": 21.75816,
        "high": 21.85153,
        "low": 21.65555,
        "close": 21.80602,
        "tick_volume": 660704,
        "spread": 1,
        "real_volume": 0
      },
      {
        "time": "2025-08-31T00:00:00+00:00",
        "open": 21.76397,
        "high": 22.00652,
        "low": 21.68913,
        "close": 21.90649,
        "tick_volume": 700937,
        "spread": 0,
        "real_volume": 0
      },
      {
        "time": "2025-09-07T00:00:00+00:00",
        "open": 21.83381,
        "high": 21.96251,
        "low": 21.62455,
        "close": 21.642220000000002,
        "tick_volume": 718872,
        "spread": 0,
        "real_volume": 0
      },
      {
        "time": "2025-09-14T00:00:00+00:00",
        "open": 21.62731,
        "high": 21.75478,
        "low": 21.51785,
        "close": 21.61659,
        "tick_volume": 693799,
        "spread": 0,
        "real_volume": 0
      },
      {
        "time": "2025-09-21T00:00:00+00:00",
        "open": 21.49695,
        "high": 21.71628,
        "low": 21.44369,
        "close": 21.47831,
        "tick_volume": 729931,
        "spread": 0,
        "real_volume": 0
      },
      {
        "time": "2025-09-28T00:00:00+00:00",
        "open": 21.48539,
        "high": 21.67213,
        "low": 21.41147,
        "close": 21.60435,
        "tick_volume": 742169,
        "spread": 0,
        "real_volume": 0
      },
      {
        "time": "2025-10-05T00:00:00+00:00",
        "open": 21.50627,
        "high": 21.65749,
        "low": 21.23531,
        "close": 21.62349,
        "tick_volume": 748160,
        "spread": 0,
        "real_volume": 0
      },
      {
        "time": "2025-10-12T00:00:00+00:00",
        "open": 21.4495,
        "high": 21.70481,
        "low": 21.29558,
        "close": 21.40414,
        "tick_volume": 861837,
        "spread": 0,
        "real_volume": 0
      },
      {
        "time": "2025-10-19T00:00:00+00:00",
        "open": 21.42275,
        "high": 21.48717,
        "low": 21.29745,
        "close": 21.4597,
        "tick_volume": 750378,
        "spread": 0,
        "real_volume": 0
      },
      {
        "time": "2025-10-26T00:00:00+00:00",
        "open": 21.39729,
        "high": 21.51791,
        "low": 21.36328,
        "close": 21.42749,
        "tick_volume": 717704,
        "spread": 0,
        "real_volume": 0
      },
      {
        "time": "2025-11-02T00:00:00+00:00",
        "open": 21.36118,
        "high": 21.55949,
        "low": 21.26642,
        "close": 21.32616,
        "tick_volume": 794931,
        "spread": 0,
        "real_volume": 0
      },
      {
        "time": "2025-11-09T00:00:00+00:00",
        "open": 21.29477,
        "high": 21.42425,
        "low": 21.15078,
        "close": 21.26641,
        "tick_volume": 944785,
        "spread": 0,
        "real_volume": 0
      },
      {
        "time": "2025-11-16T00:00:00+00:00",
        "open": 21.23977,
        "high": 21.44554,
        "low": 21.10521,
        "close": 21.2767,
        "tick_volume": 1135652,
        "spread": 0,
        "real_volume": 0
      },
      {
        "time": "2025-11-23T00:00:00+00:00",
        "open": 21.25077,
        "high": 21.39633,
        "low": 21.18836,
        "close": 21.20433,
        "tick_volume": 1024014,
        "spread": 0,
        "real_volume": 0
      },
      {
        "time": "2025-11-30T00:00:00+00:00",
        "open": 21.23568,
        "high": 21.36111,
        "low": 21.14489,
        "close": 21.16253,
        "tick_volume": 730535,
        "spread": 0,
        "real_volume": 0
      },
      {
        "time": "2025-12-07T00:00:00+00:00",
        "open": 21.15731,
        "high": 21.3114,
        "low": 21.12638,
        "close": 21.14525,
        "tick_volume": 570118,
        "spread": 1,
        "real_volume": 0
      },
      {
        "time": "2025-12-14T00:00:00+00:00",
        "open": 21.13593,
        "high": 21.20107,
        "low": 21.04066,
        "close": 21.10497,
        "tick_volume": 590480,
        "spread": 0,
        "real_volume": 0
      },
      {
        "time": "2025-12-21T00:00:00+00:00",
        "open": 21.09224,
        "high": 21.18577,
        "low": 21.02045,
        "close": 21.06873,
        "tick_volume": 440784,
        "spread": 2,
        "real_volume": 0
      },
      {
        "time": "2025-12-28T00:00:00+00:00",
        "open": 21.04993,
        "high": 21.19049,
        "low": 20.96813,
        "close": 20.971049999999998,
        "tick_volume": 438456,
        "spread": 1,
        "real_volume": 0
      },
      {
        "time": "2026-01-04T00:00:00+00:00",
        "open": 20.98713,
        "high": 21.07934,
        "low": 20.89405,
        "close": 20.90751,
        "tick_volume": 616602,
        "spread": 0,
        "real_volume": 0
      },
      {
        "time": "2026-01-11T00:00:00+00:00",
        "open": 20.88599,
        "high": 20.96068,
        "low": 20.42498,
        "close": 20.43962,
        "tick_volume": 637353,
        "spread": 2,
        "real_volume": 0
      },
      {
        "time": "2026-01-18T00:00:00+00:00",
        "open": 20.46007,
        "high": 20.74616,
        "low": 20.36075,
        "close": 20.53351,
        "tick_volume": 756948,
        "spread": 0,
        "real_volume": 0
      },
      {
        "time": "2026-01-25T00:00:00+00:00",
        "open": 20.57807,
        "high": 20.73727,
        "low": 20.46315,
        "close": 20.69649,
        "tick_volume": 1092101,
        "spread": 0,
        "real_volume": 0
      },
      {
        "time": "2026-02-01T00:00:00+00:00",
        "open": 20.65669,
        "high": 20.80685,
        "low": 20.30921,
        "close": 20.39822,
        "tick_volume": 1108510,
        "spread": 0,
        "real_volume": 0
      },
      {
        "time": "2026-02-08T00:00:00+00:00",
        "open": 20.33801,
        "high": 20.56288,
        "low": 20.33801,
        "close": 20.36158,
        "tick_volume": 807005,
        "spread": 0,
        "real_volume": 0
      },
      {
        "time": "2026-02-15T00:00:00+00:00",
        "open": 20.35341,
        "high": 20.38098,
        "low": 20.16592,
        "close": 20.17748,
        "tick_volume": 692374,
        "spread": 0,
        "real_volume": 0
      },
      {
        "time": "2026-02-22T00:00:00+00:00",
        "open": 20.19375,
        "high": 20.39343,
        "low": 20.18669,
        "close": 20.34336,
        "tick_volume": 643668,
        "spread": 0,
        "real_volume": 0
      },
      {
        "time": "2026-03-01T00:00:00+00:00",
        "open": 20.39694,
        "high": 20.69155,
        "low": 20.18315,
        "close": 20.6582,
        "tick_volume": 1224118,
        "spread": 0,
        "real_volume": 0
      },
      {
        "time": "2026-03-08T00:00:00+00:00",
        "open": 20.61677,
        "high": 20.76933,
        "low": 20.33698,
        "close": 20.48049,
        "tick_volume": 1132808,
        "spread": 0,
        "real_volume": 0
      },
      {
        "time": "2026-03-15T00:00:00+00:00",
        "open": 20.44119,
        "high": 20.63444,
        "low": 20.30158,
        "close": 20.56387,
        "tick_volume": 679461,
        "spread": 0,
        "real_volume": 0
      }
    ],
    "month": [
      {
        "time": "2024-04-01T00:00:00+00:00",
        "open": 17.83347,
        "high": 18.9543,
        "low": 17.54544,
        "close": 18.27879,
        "tick_volume": 2404097,
        "spread": 0,
        "real_volume": 0
      },
      {
        "time": "2024-05-01T00:00:00+00:00",
        "open": 18.27888,
        "high": 18.52138,
        "low": 17.93675,
        "close": 18.4136,
        "tick_volume": 2336342,
        "spread": 0,
        "real_volume": 0
      },
      {
        "time": "2024-06-01T00:00:00+00:00",
        "open": 18.37319,
        "high": 20.56144,
        "low": 18.3575,
        "close": 19.6383,
        "tick_volume": 2245138,
        "spread": 0,
        "real_volume": 0
      },
      {
        "time": "2024-07-01T00:00:00+00:00",
        "open": 19.60159,
        "high": 20.47093,
        "low": 19.19488,
        "close": 20.14882,
        "tick_volume": 2775375,
        "spread": 0,
        "real_volume": 0
      },
      {
        "time": "2024-08-01T00:00:00+00:00",
        "open": 20.14945,
        "high": 22.13576,
        "low": 19.89958,
        "close": 21.77595,
        "tick_volume": 3547812,
        "spread": 0,
        "real_volume": 0
      },
      {
        "time": "2024-09-01T00:00:00+00:00",
        "open": 21.73107,
        "high": 22.40181,
        "low": 21.19453,
        "close": 21.91204,
        "tick_volume": 3009386,
        "spread": 0,
        "real_volume": 0
      },
      {
        "time": "2024-10-01T00:00:00+00:00",
        "open": 21.88723,
        "high": 21.96309,
        "low": 20.9502,
        "close": 21.79994,
        "tick_volume": 2622692,
        "spread": 468,
        "real_volume": 0
      },
      {
        "time": "2024-11-01T00:00:00+00:00",
        "open": 21.78084,
        "high": 22.34787,
        "low": 21.18956,
        "close": 21.54208,
        "tick_volume": 2556205,
        "spread": 470,
        "real_volume": 0
      },
      {
        "time": "2024-12-01T00:00:00+00:00",
        "open": 21.47604,
        "high": 21.64754,
        "low": 20.8859,
        "close": 21.55715,
        "tick_volume": 2185110,
        "spread": 0,
        "real_volume": 0
      },
      {
        "time": "2025-01-01T00:00:00+00:00",
        "open": 21.50378,
        "high": 21.75532,
        "low": 20.96014,
        "close": 21.39876,
        "tick_volume": 3753408,
        "spread": 476,
        "real_volume": 0
      },
      {
        "time": "2025-02-01T00:00:00+00:00",
        "open": 21.70103,
        "high": 21.77143,
        "low": 20.95582,
        "close": 21.2966,
        "tick_volume": 3343752,
        "spread": 478,
        "real_volume": 0
      },
      {
        "time": "2025-03-01T00:00:00+00:00",
        "open": 21.35613,
        "high": 22.25267,
        "low": 21.28312,
        "close": 22.11304,
        "tick_volume": 3436390,
        "spread": 481,
        "real_volume": 0
      },
      {
        "time": "2025-04-01T00:00:00+00:00",
        "open": 22.11741,
        "high": 23.52341,
        "low": 21.80377,
        "close": 22.21315,
        "tick_volume": 3955680,
        "spread": 0,
        "real_volume": 0
      },
      {
        "time": "2025-05-01T00:00:00+00:00",
        "open": 22.17666,
        "high": 22.45298,
        "low": 21.58609,
        "close": 22.04749,
        "tick_volume": 2919600,
        "spread": 0,
        "real_volume": 0
      },
      {
        "time": "2025-06-01T00:00:00+00:00",
        "open": 21.86275,
        "high": 22.18039,
        "low": 21.62037,
        "close": 22.09452,
        "tick_volume": 2907128,
        "spread": 0,
        "real_volume": 0
      },
      {
        "time": "2025-07-01T00:00:00+00:00",
        "open": 22.09452,
        "high": 22.19145,
        "low": 21.45281,
        "close": 21.5381,
        "tick_volume": 3246727,
        "spread": 0,
        "real_volume": 0
      },
      {
        "time": "2025-08-01T00:00:00+00:00",
        "open": 21.53364,
        "high": 22.02568,
        "low": 21.51906,
        "close": 21.80602,
        "tick_volume": 2957033,
        "spread": 0,
        "real_volume": 0
      },
      {
        "time": "2025-09-01T00:00:00+00:00",
        "open": 21.76397,
        "high": 22.00652,
        "low": 21.44369,
        "close": 21.48003,
        "tick_volume": 3131274,
        "spread": 0,
        "real_volume": 0
      },
      {
        "time": "2025-10-01T00:00:00+00:00",
        "open": 21.48004,
        "high": 21.70481,
        "low": 21.23531,
        "close": 21.42749,
        "tick_volume": 3532513,
        "spread": 0,
        "real_volume": 0
      },
      {
        "time": "2025-11-01T00:00:00+00:00",
        "open": 21.36118,
        "high": 21.55949,
        "low": 21.10521,
        "close": 21.20433,
        "tick_volume": 3899382,
        "spread": 0,
        "real_volume": 0
      },
      {
        "time": "2025-12-01T00:00:00+00:00",
        "open": 21.23568,
        "high": 21.36111,
        "low": 20.97765,
        "close": 21.14615,
        "tick_volume": 2665710,
        "spread": 0,
        "real_volume": 0
      },
      {
        "time": "2026-01-01T00:00:00+00:00",
        "open": 21.13775,
        "high": 21.15625,
        "low": 20.36075,
        "close": 20.69649,
        "tick_volume": 3207667,
        "spread": 0,
        "real_volume": 0
      },
      {
        "time": "2026-02-01T00:00:00+00:00",
        "open": 20.65669,
        "high": 20.80685,
        "low": 20.16592,
        "close": 20.34336,
        "tick_volume": 3251557,
        "spread": 0,
        "real_volume": 0
      },
      {
        "time": "2026-03-01T00:00:00+00:00",
        "open": 20.39694,
        "high": 20.76933,
        "low": 20.18315,
        "close": 20.56387,
        "tick_volume": 3036387,
        "spread": 0,
        "real_volume": 0
      }
    ]
  },
  "oscillators": {
    "1h": {
      "rsi": [
        {
          "time": "2026-03-19T01:00:00+00:00",
          "value": 74.212097
        },
        {
          "time": "2026-03-19T02:00:00+00:00",
          "value": 74.564982
        },
        {
          "time": "2026-03-19T03:00:00+00:00",
          "value": 70.290217
        },
        {
          "time": "2026-03-19T04:00:00+00:00",
          "value": 69.851819
        },
        {
          "time": "2026-03-19T05:00:00+00:00",
          "value": 67.350604
        },
        {
          "time": "2026-03-19T06:00:00+00:00",
          "value": 64.45978
        },
        {
          "time": "2026-03-19T07:00:00+00:00",
          "value": 65.38705
        },
        {
          "time": "2026-03-19T08:00:00+00:00",
          "value": 65.631109
        },
        {
          "time": "2026-03-19T09:00:00+00:00",
          "value": 64.266502
        },
        {
          "time": "2026-03-19T10:00:00+00:00",
          "value": 67.23661
        },
        {
          "time": "2026-03-19T11:00:00+00:00",
          "value": 61.566418
        },
        {
          "time": "2026-03-19T12:00:00+00:00",
          "value": 57.617576
        },
        {
          "time": "2026-03-19T13:00:00+00:00",
          "value": 57.118861
        },
        {
          "time": "2026-03-19T14:00:00+00:00",
          "value": 59.491432
        },
        {
          "time": "2026-03-19T15:00:00+00:00",
          "value": 72.431106
        },
        {
          "time": "2026-03-19T16:00:00+00:00",
          "value": 76.969884
        }
      ],
      "ma": [
        {
          "time": "2026-03-19T06:00:00+00:00",
          "value": 20.396496
        },
        {
          "time": "2026-03-19T07:00:00+00:00",
          "value": 20.402766
        },
        {
          "time": "2026-03-19T08:00:00+00:00",
          "value": 20.408868
        },
        {
          "time": "2026-03-19T09:00:00+00:00",
          "value": 20.413402
        },
        {
          "time": "2026-03-19T10:00:00+00:00",
          "value": 20.418797
        },
        {
          "time": "2026-03-19T11:00:00+00:00",
          "value": 20.419476
        },
        {
          "time": "2026-03-19T12:00:00+00:00",
          "value": 20.421062
        },
        {
          "time": "2026-03-19T13:00:00+00:00",
          "value": 20.424246
        },
        {
          "time": "2026-03-19T14:00:00+00:00",
          "value": 20.427943
        },
        {
          "time": "2026-03-19T15:00:00+00:00",
          "value": 20.436102
        },
        {
          "time": "2026-03-19T16:00:00+00:00",
          "value": 20.44609
        }
      ]
    },
    "4h": {
      "rsi": [
        {
          "time": "2026-03-17T04:00:00+00:00",
          "value": 21.440897
        },
        {
          "time": "2026-03-17T08:00:00+00:00",
          "value": 26.283946
        },
        {
          "time": "2026-03-17T12:00:00+00:00",
          "value": 28.68095
        },
        {
          "time": "2026-03-17T16:00:00+00:00",
          "value": 34.86573
        },
        {
          "time": "2026-03-17T20:00:00+00:00",
          "value": 32.150676
        },
        {
          "time": "2026-03-18T00:00:00+00:00",
          "value": 30.591948
        },
        {
          "time": "2026-03-18T04:00:00+00:00",
          "value": 30.547962
        },
        {
          "time": "2026-03-18T08:00:00+00:00",
          "value": 27.049717
        },
        {
          "time": "2026-03-18T12:00:00+00:00",
          "value": 44.737451
        },
        {
          "time": "2026-03-18T16:00:00+00:00",
          "value": 38.66159
        },
        {
          "time": "2026-03-18T20:00:00+00:00",
          "value": 49.105453
        },
        {
          "time": "2026-03-19T00:00:00+00:00",
          "value": 49.771652
        },
        {
          "time": "2026-03-19T04:00:00+00:00",
          "value": 48.143671
        },
        {
          "time": "2026-03-19T08:00:00+00:00",
          "value": 47.779087
        },
        {
          "time": "2026-03-19T12:00:00+00:00",
          "value": 56.482428
        },
        {
          "time": "2026-03-19T16:00:00+00:00",
          "value": 60.745209
        }
      ],
      "ma": [
        {
          "time": "2026-03-18T00:00:00+00:00",
          "value": 20.425277
        },
        {
          "time": "2026-03-18T04:00:00+00:00",
          "value": 20.41506
        },
        {
          "time": "2026-03-18T08:00:00+00:00",
          "value": 20.403848
        },
        {
          "time": "2026-03-18T12:00:00+00:00",
          "value": 20.398707
        },
        {
          "time": "2026-03-18T16:00:00+00:00",
          "value": 20.391866
        },
        {
          "time": "2026-03-18T20:00:00+00:00",
          "value": 20.392741
        },
        {
          "time": "2026-03-19T00:00:00+00:00",
          "value": 20.390935
        },
        {
          "time": "2026-03-19T04:00:00+00:00",
          "value": 20.38865
        },
        {
          "time": "2026-03-19T08:00:00+00:00",
          "value": 20.388733
        },
        {
          "time": "2026-03-19T12:00:00+00:00",
          "value": 20.392488
        },
        {
          "time": "2026-03-19T16:00:00+00:00",
          "value": 20.3983
        }
      ]
    },
    "day": {
      "rsi": [
        {
          "time": "2026-02-26T00:00:00+00:00",
          "value": 43.656983
        },
        {
          "time": "2026-02-27T00:00:00+00:00",
          "value": 47.471861
        },
        {
          "time": "2026-03-02T00:00:00+00:00",
          "value": 41.335791
        },
        {
          "time": "2026-03-03T00:00:00+00:00",
          "value": 57.062116
        },
        {
          "time": "2026-03-04T00:00:00+00:00",
          "value": 51.67417
        },
        {
          "time": "2026-03-05T00:00:00+00:00",
          "value": 56.531039
        },
        {
          "time": "2026-03-06T00:00:00+00:00",
          "value": 59.701055
        },
        {
          "time": "2026-03-09T00:00:00+00:00",
          "value": 51.716757
        },
        {
          "time": "2026-03-10T00:00:00+00:00",
          "value": 50.015408
        },
        {
          "time": "2026-03-11T00:00:00+00:00",
          "value": 50.721792
        },
        {
          "time": "2026-03-12T00:00:00+00:00",
          "value": 55.003107
        },
        {
          "time": "2026-03-13T00:00:00+00:00",
          "value": 51.786335
        },
        {
          "time": "2026-03-16T00:00:00+00:00",
          "value": 46.357979
        },
        {
          "time": "2026-03-17T00:00:00+00:00",
          "value": 47.577266
        },
        {
          "time": "2026-03-18T00:00:00+00:00",
          "value": 50.697522
        },
        {
          "time": "2026-03-19T00:00:00+00:00",
          "value": 55.31725
        }
      ],
      "ma": [
        {
          "time": "2026-03-05T00:00:00+00:00",
          "value": 20.355895
        },
        {
          "time": "2026-03-06T00:00:00+00:00",
          "value": 20.368894
        },
        {
          "time": "2026-03-09T00:00:00+00:00",
          "value": 20.368452
        },
        {
          "time": "2026-03-10T00:00:00+00:00",
          "value": 20.367299
        },
        {
          "time": "2026-03-11T00:00:00+00:00",
          "value": 20.369868
        },
        {
          "time": "2026-03-12T00:00:00+00:00",
          "value": 20.375502
        },
        {
          "time": "2026-03-13T00:00:00+00:00",
          "value": 20.381448
        },
        {
          "time": "2026-03-16T00:00:00+00:00",
          "value": 20.38144
        },
        {
          "time": "2026-03-17T00:00:00+00:00",
          "value": 20.384938
        },
        {
          "time": "2026-03-18T00:00:00+00:00",
          "value": 20.393615
        },
        {
          "time": "2026-03-19T00:00:00+00:00",
          "value": 20.406542
        }
      ]
    },
    "week": {
      "rsi": [
        {
          "time": "2025-11-30T00:00:00+00:00",
          "value": 24.595536
        },
        {
          "time": "2025-12-07T00:00:00+00:00",
          "value": 24.239373
        },
        {
          "time": "2025-12-14T00:00:00+00:00",
          "value": 23.389143
        },
        {
          "time": "2025-12-21T00:00:00+00:00",
          "value": 22.62037
        },
        {
          "time": "2025-12-28T00:00:00+00:00",
          "value": 20.650173
        },
        {
          "time": "2026-01-04T00:00:00+00:00",
          "value": 19.46266
        },
        {
          "time": "2026-01-11T00:00:00+00:00",
          "value": 13.366911
        },
        {
          "time": "2026-01-18T00:00:00+00:00",
          "value": 18.858857
        },
        {
          "time": "2026-01-25T00:00:00+00:00",
          "value": 27.455813
        },
        {
          "time": "2026-02-01T00:00:00+00:00",
          "value": 22.712982
        },
        {
          "time": "2026-02-08T00:00:00+00:00",
          "value": 22.205529
        },
        {
          "time": "2026-02-15T00:00:00+00:00",
          "value": 19.810556
        },
        {
          "time": "2026-02-22T00:00:00+00:00",
          "value": 27.407773
        },
        {
          "time": "2026-03-01T00:00:00+00:00",
          "value": 39.184672
        },
        {
          "time": "2026-03-08T00:00:00+00:00",
          "value": 35.667305
        },
        {
          "time": "2026-03-15T00:00:00+00:00",
          "value": 38.458587
        }
      ],
      "ma": [
        {
          "time": "2026-01-04T00:00:00+00:00",
          "value": 21.370122
        },
        {
          "time": "2026-01-11T00:00:00+00:00",
          "value": 21.301802
        },
        {
          "time": "2026-01-18T00:00:00+00:00",
          "value": 21.233153
        },
        {
          "time": "2026-01-25T00:00:00+00:00",
          "value": 21.185866
        },
        {
          "time": "2026-02-01T00:00:00+00:00",
          "value": 21.124948
        },
        {
          "time": "2026-02-08T00:00:00+00:00",
          "value": 21.069111
        },
        {
          "time": "2026-02-15T00:00:00+00:00",
          "value": 20.997768
        },
        {
          "time": "2026-02-22T00:00:00+00:00",
          "value": 20.933761
        },
        {
          "time": "2026-03-01T00:00:00+00:00",
          "value": 20.896465
        },
        {
          "time": "2026-03-08T00:00:00+00:00",
          "value": 20.847504
        },
        {
          "time": "2026-03-15T00:00:00+00:00",
          "value": 20.804323
        }
      ]
    },
    "month": {
      "rsi": [
        {
          "time": "2025-06-01T00:00:00+00:00",
          "value": 85.278112
        },
        {
          "time": "2025-07-01T00:00:00+00:00",
          "value": 76.771703
        },
        {
          "time": "2025-08-01T00:00:00+00:00",
          "value": 77.914084
        },
        {
          "time": "2025-09-01T00:00:00+00:00",
          "value": 73.197028
        },
        {
          "time": "2025-10-01T00:00:00+00:00",
          "value": 72.435862
        },
        {
          "time": "2025-11-01T00:00:00+00:00",
          "value": 69.146823
        },
        {
          "time": "2025-12-01T00:00:00+00:00",
          "value": 68.276405
        },
        {
          "time": "2026-01-01T00:00:00+00:00",
          "value": 61.801275
        },
        {
          "time": "2026-02-01T00:00:00+00:00",
          "value": 57.212431
        },
        {
          "time": "2026-03-01T00:00:00+00:00",
          "value": 59.247319
        }
      ],
      "ma": [
        {
          "time": "2025-11-01T00:00:00+00:00",
          "value": 21.18431
        },
        {
          "time": "2025-12-01T00:00:00+00:00",
          "value": 21.327678
        },
        {
          "time": "2026-01-01T00:00:00+00:00",
          "value": 21.441822
        },
        {
          "time": "2026-02-01T00:00:00+00:00",
          "value": 21.477075
        },
        {
          "time": "2026-03-01T00:00:00+00:00",
          "value": 21.497828
        }
      ]
    }
  }
}